setup.cfg
setup.py
requestcep/__init__.py
requestcep/requestcep.py
requestcep.egg-info/PKG-INFO
requestcep.egg-info/SOURCES.txt
requestcep.egg-info/dependency_links.txt
requestcep.egg-info/requires.txt
requestcep.egg-info/top_level.txt