Metadata-Version: 1.1
Name: requestcep
Version: 1.0
Summary: Obtenha facilmente os dados do CEP.
Home-page: https://gitlab.com/AnDroidEL/requestcep
Author: Emanuel A. Leite
Author-email: androidel@openmailbox.org
License: MIT
Download-URL: https://gitlab.com/AnDroidEL/requestcep/tags/1.0
Keywords: api request cep
Platform: UNKNOWN
Classifier: Development Status :: 5 - Production/Stable
Classifier: Programming Language :: Python :: 3
Classifier: Programming Language :: Python :: 3.5
